himl/__init__.py
himl/_version.py
himl/config_generator.py
himl/config_merger.py
himl/filter_rules.py
himl/inject_env.py
himl/inject_secrets.py
himl/interpolation.py
himl/main.py
himl/python_compat.py
himl/remote_state.py
himl/secret_resolvers.py
himl/simples3.py
himl/simplesops.py
himl/simplessm.py
himl/simplevault.py
himl-0.20.0.dist-info/licenses/LICENSE
himl-0.20.0.dist-info/METADATA
himl-0.20.0.dist-info/WHEEL
himl-0.20.0.dist-info/entry_points.txt
himl-0.20.0.dist-info/top_level.txt
himl-0.20.0.dist-info/RECORD
