Metadata-Version: 2.4
Name: himl
Version: 0.20.0
Summary: A hierarchical config using YAML in Python
Author-email: Adobe <noreply@adobe.com>
License-Expression: Apache-2.0
Project-URL: Homepage, https://github.com/adobe/himl
Project-URL: Repository, https://github.com/adobe/himl
Project-URL: Documentation, https://github.com/adobe/himl#readme
Project-URL: Bug Tracker, https://github.com/adobe/himl/issues
Classifier: Development Status :: 4 - Beta
Classifier: Intended Audience :: Developers
Classifier: Programming Language :: Python :: 3
Classifier: Programming Language :: Python :: 3.10
Classifier: Programming Language :: Python :: 3.11
Classifier: Programming Language :: Python :: 3.12
Classifier: Programming Language :: Python :: 3.13
Classifier: Programming Language :: Python :: 3.14
Classifier: Topic :: Software Development :: Libraries :: Python Modules
Classifier: Topic :: System :: Systems Administration
Classifier: Topic :: Utilities
Requires-Python: >=3.10
License-File: LICENSE
Requires-Dist: PyYAML==6.0.3
Requires-Dist: deepmerge==2.0
Requires-Dist: pathlib2==2.3.7.post1
Provides-Extra: s3
Requires-Dist: boto3==1.42.9; extra == "s3"
Provides-Extra: aws
Requires-Dist: boto3==1.42.9; extra == "aws"
Provides-Extra: vault
Requires-Dist: hvac==2.4.0; extra == "vault"
Provides-Extra: all
Requires-Dist: boto3==1.42.9; extra == "all"
Requires-Dist: hvac==2.4.0; extra == "all"
Provides-Extra: dev
Requires-Dist: pytest==9.0.2; extra == "dev"
Requires-Dist: pytest-cov==7.0.0; extra == "dev"
Requires-Dist: pytest-mock==3.15.1; extra == "dev"
Requires-Dist: pytest-xdist==3.8.0; extra == "dev"
Requires-Dist: coverage[toml]==7.13.0; extra == "dev"
Requires-Dist: black==25.12.0; extra == "dev"
Requires-Dist: flake8==7.3.0; extra == "dev"
Requires-Dist: mypy==1.19.1; extra == "dev"
Requires-Dist: types-PyYAML==6.0.12.20250915; extra == "dev"
Requires-Dist: boto3==1.42.9; extra == "dev"
Requires-Dist: hvac==2.4.0; extra == "dev"
Requires-Dist: bump-my-version==1.2.5; extra == "dev"
Requires-Dist: build==1.3.0; extra == "dev"
Requires-Dist: twine==6.2.0; extra == "dev"
Dynamic: license-file
